wavyfm/__init__.py
wavyfm/auth.py
wavyfm/client.py
wavyfm/error.py
wavyfm/metrics.py
wavyfm/users.py
wavyfm/util.py
wavyfm-1.0.3.dist-info/LICENSE.md
wavyfm-1.0.3.dist-info/METADATA
wavyfm-1.0.3.dist-info/WHEEL
wavyfm-1.0.3.dist-info/top_level.txt
wavyfm-1.0.3.dist-info/RECORD
