Metadata-Version: 2.1
Name: wavyfm
Version: 1.0.3
Summary: Official Python library for wavy.fm
Home-page: https://wavy.fm/developers
Author: Aram Peres
Author-email: aram.peres@wavy.fm
License: LICENSE.md
Project-URL: Documentation, https://github.com/wavy/wavyfm-python
Project-URL: Source, https://github.com/wavy/wavyfm-python
Platform: UNKNOWN
Requires-Dist: requests (>=2.26.0)
Provides-Extra: doc
Provides-Extra: test
Requires-Dist: mock (==2.0.0) ; extra == 'test'
